<?xml version="1.0" encoding="utf-8"?>
<xd:acceleratorMap xmlns:xd="http://www.xilinx.com/xidane" xd:functionName="ultra_net" xd:componentRef="ultra_net" xd:initiationInterval="x" xd:clockPeriod="4.000" xd:sequential="true" xd:hostMachine="64" xd:reset="control">
  <xd:controlReg xd:name="control" xd:interfaceRef="s_axi_control" xd:busTypeRef="axilite" xd:type="generic_axi_lite" xd:offset="0x0"/>
  <xd:arg xd:name="in.data" xd:originalName="in" xd:direction="in" xd:interfaceRef="in_r" xd:busTypeRef="axis" xd:dataWidth="64"/>
  <xd:arg xd:name="in.last" xd:originalName="in" xd:direction="in" xd:interfaceRef="in_r" xd:busTypeRef="axis" xd:dataWidth="1"/>
  <xd:arg xd:name="in.keep" xd:originalName="in" xd:direction="in" xd:interfaceRef="in_r" xd:busTypeRef="axis" xd:dataWidth="8"/>
  <xd:arg xd:name="out.data" xd:originalName="out" xd:direction="out" xd:interfaceRef="out_r" xd:busTypeRef="axis" xd:dataWidth="64"/>
  <xd:arg xd:name="out.last" xd:originalName="out" xd:direction="out" xd:interfaceRef="out_r" xd:busTypeRef="axis" xd:dataWidth="1"/>
  <xd:arg xd:name="out.keep" xd:originalName="out" xd:direction="out" xd:interfaceRef="out_r" xd:busTypeRef="axis" xd:dataWidth="8"/>
  <xd:arg xd:name="reps" xd:originalName="reps" xd:direction="in" xd:interfaceRef="s_axi_control" xd:busTypeRef="axilite" xd:offset="0x10" xd:handshakeRef="ap_none" xd:dataWidth="32"/>
  <xd:latencyEstimates xd:best-case="undef" xd:worst-case="undef" xd:average-case="undef"/>
  <xd:resourceEstimates xd:LUT="87670" xd:FF="72686" xd:BRAM="232" xd:DSP="380"/>
</xd:acceleratorMap>
