<profile>

<ReportVersion>
<Version>2019.2</Version>
</ReportVersion>

<UserAssignments>
<unit>ns</unit>
<ProductFamily>zynquplus</ProductFamily>
<Part>xczu3eg-sbva484-1-e</Part>
<TopModelName>stream_out_data_4</TopModelName>
<TargetClockPeriod>4.00</TargetClockPeriod>
<ClockUncertainty>0.50</ClockUncertainty>
</UserAssignments>

<PerformanceEstimates>
<PipelineType>none</PipelineType>
<SummaryOfTimingAnalysis>
<unit>ns</unit>
<EstimatedClockPeriod>3.471</EstimatedClockPeriod>
</SummaryOfTimingAnalysis>
<SummaryOfOverallLatency>
<unit>clock cycles</unit>
<Best-caseLatency>1</Best-caseLatency>
<Average-caseLatency>8451</Average-caseLatency>
<Worst-caseLatency>16900</Worst-caseLatency>
<Best-caseRealTimeLatency>4.000 ns</Best-caseRealTimeLatency>
<Average-caseRealTimeLatency>33.804 us</Average-caseRealTimeLatency>
<Worst-caseRealTimeLatency>67.600 us</Worst-caseRealTimeLatency>
<Interval-min>1</Interval-min>
<Interval-max>16900</Interval-max>
</SummaryOfOverallLatency>
<SummaryOfLoopLatency>
<Loop1>
<TripCount>16896</TripCount>
<Latency>16898</Latency>
<PipelineII>1</PipelineII>
<PipelineDepth>4</PipelineDepth>
</Loop1>
</SummaryOfLoopLatency>
</PerformanceEstimates>

<AreaEstimates>
<Resources>
<BRAM_18K>0</BRAM_18K>
<DSP48E>1</DSP48E>
<FF>169</FF>
<LUT>368</LUT>
<URAM>0</URAM>
</Resources>
<AvailableResources>
<BRAM_18K>432</BRAM_18K>
<DSP48E>360</DSP48E>
<FF>141120</FF>
<LUT>70560</LUT>
<URAM>0</URAM>
</AvailableResources>
</AreaEstimates>

<InterfaceSummary>
<RtlPorts>
<name>ap_clk</name>
<Object>stream_out_data.4</Object>
<Type>return value</Type>
<Scope></Scope>
<IOProtocol>ap_ctrl_hs</IOProtocol>
<IOConfig></IOConfig>
<Dir>in</Dir>
<Bits>1</Bits>
<Attribute>control</Attribute>
</RtlPorts>
<RtlPorts>
<name>ap_rst</name>
<Object>stream_out_data.4</Object>
<Type>return value</Type>
<Scope></Scope>
<IOProtocol>ap_ctrl_hs</IOProtocol>
<IOConfig></IOConfig>
<Dir>in</Dir>
<Bits>1</Bits>
<Attribute>control</Attribute>
</RtlPorts>
<RtlPorts>
<name>ap_start</name>
<Object>stream_out_data.4</Object>
<Type>return value</Type>
<Scope></Scope>
<IOProtocol>ap_ctrl_hs</IOProtocol>
<IOConfig></IOConfig>
<Dir>in</Dir>
<Bits>1</Bits>
<Attribute>control</Attribute>
</RtlPorts>
<RtlPorts>
<name>ap_done</name>
<Object>stream_out_data.4</Object>
<Type>return value</Type>
<Scope></Scope>
<IOProtocol>ap_ctrl_hs</IOProtocol>
<IOConfig></IOConfig>
<Dir>out</Dir>
<Bits>1</Bits>
<Attribute>control</Attribute>
</RtlPorts>
<RtlPorts>
<name>ap_idle</name>
<Object>stream_out_data.4</Object>
<Type>return value</Type>
<Scope></Scope>
<IOProtocol>ap_ctrl_hs</IOProtocol>
<IOConfig></IOConfig>
<Dir>out</Dir>
<Bits>1</Bits>
<Attribute>control</Attribute>
</RtlPorts>
<RtlPorts>
<name>ap_ready</name>
<Object>stream_out_data.4</Object>
<Type>return value</Type>
<Scope></Scope>
<IOProtocol>ap_ctrl_hs</IOProtocol>
<IOConfig></IOConfig>
<Dir>out</Dir>
<Bits>1</Bits>
<Attribute>control</Attribute>
</RtlPorts>
<RtlPorts>
<name>out_V_V_din</name>
<Object>out_V_V</Object>
<Type>pointer</Type>
<Scope></Scope>
<IOProtocol>ap_fifo</IOProtocol>
<IOConfig></IOConfig>
<Dir>out</Dir>
<Bits>32</Bits>
<Attribute>control</Attribute>
</RtlPorts>
<RtlPorts>
<name>out_V_V_full_n</name>
<Object>out_V_V</Object>
<Type>pointer</Type>
<Scope></Scope>
<IOProtocol>ap_fifo</IOProtocol>
<IOConfig></IOConfig>
<Dir>in</Dir>
<Bits>1</Bits>
<Attribute>control</Attribute>
</RtlPorts>
<RtlPorts>
<name>out_V_V_write</name>
<Object>out_V_V</Object>
<Type>pointer</Type>
<Scope></Scope>
<IOProtocol>ap_fifo</IOProtocol>
<IOConfig></IOConfig>
<Dir>out</Dir>
<Bits>1</Bits>
<Attribute>control</Attribute>
</RtlPorts>
<RtlPorts>
<name>row_buffer_0_V_address0</name>
<Object>row_buffer_0_V</Object>
<Type>array</Type>
<Scope></Scope>
<IOProtocol>ap_memory</IOProtocol>
<IOConfig></IOConfig>
<Dir>out</Dir>
<Bits>10</Bits>
<Attribute>address</Attribute>
</RtlPorts>
<RtlPorts>
<name>row_buffer_0_V_ce0</name>
<Object>row_buffer_0_V</Object>
<Type>array</Type>
<Scope></Scope>
<IOProtocol>ap_memory</IOProtocol>
<IOConfig></IOConfig>
<Dir>out</Dir>
<Bits>1</Bits>
<Attribute>control</Attribute>
</RtlPorts>
<RtlPorts>
<name>row_buffer_0_V_q0</name>
<Object>row_buffer_0_V</Object>
<Type>array</Type>
<Scope></Scope>
<IOProtocol>ap_memory</IOProtocol>
<IOConfig></IOConfig>
<Dir>in</Dir>
<Bits>16</Bits>
<Attribute>data</Attribute>
</RtlPorts>
<RtlPorts>
<name>row_buffer_1_V_address0</name>
<Object>row_buffer_1_V</Object>
<Type>array</Type>
<Scope></Scope>
<IOProtocol>ap_memory</IOProtocol>
<IOConfig></IOConfig>
<Dir>out</Dir>
<Bits>10</Bits>
<Attribute>address</Attribute>
</RtlPorts>
<RtlPorts>
<name>row_buffer_1_V_ce0</name>
<Object>row_buffer_1_V</Object>
<Type>array</Type>
<Scope></Scope>
<IOProtocol>ap_memory</IOProtocol>
<IOConfig></IOConfig>
<Dir>out</Dir>
<Bits>1</Bits>
<Attribute>control</Attribute>
</RtlPorts>
<RtlPorts>
<name>row_buffer_1_V_q0</name>
<Object>row_buffer_1_V</Object>
<Type>array</Type>
<Scope></Scope>
<IOProtocol>ap_memory</IOProtocol>
<IOConfig></IOConfig>
<Dir>in</Dir>
<Bits>16</Bits>
<Attribute>data</Attribute>
</RtlPorts>
<RtlPorts>
<name>skip_flag</name>
<Object>skip_flag</Object>
<Type>scalar</Type>
<Scope></Scope>
<IOProtocol>ap_none</IOProtocol>
<IOConfig></IOConfig>
<Dir>in</Dir>
<Bits>1</Bits>
<Attribute>data</Attribute>
</RtlPorts>
<RtlPorts>
<name>outRowIdx_V</name>
<Object>outRowIdx_V</Object>
<Type>scalar</Type>
<Scope></Scope>
<IOProtocol>ap_none</IOProtocol>
<IOConfig></IOConfig>
<Dir>in</Dir>
<Bits>10</Bits>
<Attribute>data</Attribute>
</RtlPorts>
<RtlPorts>
<name>startRowBufferIdx_V</name>
<Object>startRowBufferIdx_V</Object>
<Type>scalar</Type>
<Scope></Scope>
<IOProtocol>ap_none</IOProtocol>
<IOConfig></IOConfig>
<Dir>in</Dir>
<Bits>2</Bits>
<Attribute>data</Attribute>
</RtlPorts>
</InterfaceSummary>

</profile>
